napari_czifile2/__init__.py
napari_czifile2/_reader.py
napari_czifile2/_version.py
napari_czifile2/io.py
napari_czifile2/napari.yaml
napari_czifile2-0.2.7.dist-info/LICENSE
napari_czifile2-0.2.7.dist-info/METADATA
napari_czifile2-0.2.7.dist-info/WHEEL
napari_czifile2-0.2.7.dist-info/entry_points.txt
napari_czifile2-0.2.7.dist-info/top_level.txt
napari_czifile2-0.2.7.dist-info/RECORD
